medify/__init__.py
medify/aws_auth.py
medify/cli.py
medify/transcribe.py
medify-0.1.dist-info/METADATA
medify-0.1.dist-info/WHEEL
medify-0.1.dist-info/entry_points.txt
medify-0.1.dist-info/top_level.txt
medify-0.1.dist-info/RECORD
