Metadata-Version: 2.2
Name: medify
Version: 0.1
Summary: A package for medical scribing using AWS Transcribe for the healthcare domain
Author: saurabh
Author-email: saurabh.patil@holbox.ai
Requires-Dist: boto3
Requires-Dist: requests
Dynamic: author
Dynamic: author-email
Dynamic: description
Dynamic: description-content-type
Dynamic: requires-dist
Dynamic: summary
